{
    "installed": [
        {
            "name": "doctrine/dbal",
            "direct-dependency": true,
            "homepage": "https://www.doctrine-project.org/projects/dbal.html",
            "source": "https://github.com/doctrine/dbal/tree/3.9.5",
            "version": "3.9.5",
            "latest": "4.2.4",
            "latest-status": "update-possible",
            "description": "Powerful PHP database abstraction layer (DBAL) with many features for database schema introspection and management.",
            "abandoned": false
        },
        {
            "name": "enlightn/security-checker",
            "direct-dependency": true,
            "homepage": null,
            "source": "https://github.com/enlightn/security-checker/tree/v1.11.0",
            "version": "v1.11.0",
            "latest": "v2.0.0",
            "latest-status": "update-possible",
            "description": "A PHP dependency vulnerabilities scanner based on the Security Advisories Database.",
            "abandoned": false
        },
        {
            "name": "phpstan/phpstan",
            "direct-dependency": true,
            "homepage": null,
            "source": "https://github.com/phpstan/phpstan-src",
            "version": "1.12.27",
            "latest": "2.1.17",
            "latest-status": "update-possible",
            "description": "PHPStan - PHP Static Analysis Tool",
            "abandoned": false
        },
        {
            "name": "phpstan/phpstan-symfony",
            "direct-dependency": true,
            "homepage": null,
            "source": "https://github.com/phpstan/phpstan-symfony/tree/1.4.15",
            "version": "1.4.15",
            "latest": "2.0.6",
            "latest-status": "update-possible",
            "description": "Symfony Framework extensions and rules for PHPStan",
            "abandoned": false
        },
        {
            "name": "phpunit/phpunit",
            "direct-dependency": true,
            "homepage": "https://phpunit.de/",
            "source": "https://github.com/sebastianbergmann/phpunit/tree/11.5.25",
            "version": "11.5.25",
            "latest": "12.2.5",
            "latest-status": "update-possible",
            "description": "The PHP Unit Testing framework.",
            "abandoned": false
        },
        {
            "name": "symfony/console",
            "direct-dependency": true,
            "homepage": "https://symfony.com",
            "source": "https://github.com/symfony/console/tree/v6.4.23",
            "version": "v6.4.23",
            "latest": "v7.3.1",
            "latest-status": "update-possible",
            "description": "Eases the creation of beautiful and testable command line interfaces",
            "abandoned": false
        },
        {
            "name": "symfony/dotenv",
            "direct-dependency": true,
            "homepage": "https://symfony.com",
            "source": "https://github.com/symfony/dotenv/tree/v6.4.16",
            "version": "v6.4.16",
            "latest": "v7.3.0",
            "latest-status": "update-possible",
            "description": "Registers environment variables from a .env file",
            "abandoned": false
        },
        {
            "name": "symfony/finder",
            "direct-dependency": true,
            "homepage": "https://symfony.com",
            "source": "https://github.com/symfony/finder/tree/v6.4.17",
            "version": "v6.4.17",
            "latest": "v7.3.0",
            "latest-status": "update-possible",
            "description": "Finds files and directories via an intuitive fluent interface",
            "abandoned": false
        },
        {
            "name": "symfony/yaml",
            "direct-dependency": true,
            "homepage": "https://symfony.com",
            "source": "https://github.com/symfony/yaml/tree/v6.4.23",
            "version": "v6.4.23",
            "latest": "v7.3.1",
            "latest-status": "update-possible",
            "description": "Loads and dumps YAML files",
            "abandoned": false
        }
    ]
}
